[
  {
    "elementType": "geometry",
    "stylers": [
      {
        "color": "#160f20"
      }
    ]
  },
  {
    "elementType": "geometry.stroke",
    "stylers": [
      {
        "color": "#271b3a"
      }
    ]
  },
  {
    "elementType": "labels.text.fill",
    "stylers": [
      {
        "color": "#a38dc7"
      }
    ]
  },
  {
    "elementType": "labels.text.stroke",
    "stylers": [
      {
        "color": "#160f20"
      }
    ]
  },
  {
    "featureType": "administrative.country",
    "elementType": "geometry.stroke",
    "stylers": [
      {
        "color": "#3f2c5c"
      }
    ]
  },
  {
    "featureType": "administrative.land_parcel",
    "elementType": "labels.text.fill",
    "stylers": [
      {
        "color": "#3f2c5c"
      }
    ]
  },
  {
    "featureType": "administrative.province",
    "elementType": "geometry.stroke",
    "stylers": [
      {
        "color": "#3f2c5c"
      }
    ]
  },
  {
    "featureType": "landscape.man_made",
    "elementType": "geometry.stroke",
    "stylers": [
      {
        "color": "#3f2c5c"
      }
    ]
  },
  {
    "featureType": "landscape.natural",
    "elementType": "geometry",
    "stylers": [
      {
        "color": "#221733"
      }
    ]
  },
  {
    "featureType": "poi",
    "elementType": "geometry.fill",
    "stylers": [
      {
        "color": "#0d0913"
      }
    ]
  },
  {
    "featureType": "poi",
    "elementType": "labels.text.fill",
    "stylers": [
      {
        "color": "#624592"
      }
    ]
  },
  {
    "featureType": "poi.government",
    "stylers": [
      {
        "visibility": "off"
      }
    ]
  },
  {
    "featureType": "poi.medical",
    "stylers": [
      {
        "visibility": "off"
      }
    ]
  },
  {
    "featureType": "poi.park",
    "elementType": "geometry.fill",
    "stylers": [
      {
        "color": "#1e162c"
      }
    ]
  },
  {
    "featureType": "poi.place_of_worship",
    "stylers": [
      {
        "visibility": "off"
      }
    ]
  },
  {
    "featureType": "poi.school",
    "elementType": "geometry",
    "stylers": [
      {
        "visibility": "off"
      }
    ]
  },
  {
    "featureType": "poi.sports_complex",
    "elementType": "geometry.fill",
    "stylers": [
      {
        "color": "#0c0a12"
      }
    ]
  },
  {
    "featureType": "road",
    "elementType": "geometry",
    "stylers": [
      {
        "color": "#3f2c5c"
      }
    ]
  },
  {
    "featureType": "road",
    "elementType": "labels.text.fill",
    "stylers": [
      {
        "color": "#000000"
      }
    ]
  },
  {
    "featureType": "road",
    "elementType": "labels.text.stroke",
    "stylers": [
      {
        "color": "#3f2c5c"
      }
    ]
  },
  {
    "featureType": "road.highway",
    "elementType": "geometry",
    "stylers": [
      {
        "color": "#49336a"
      }
    ]
  },
  {
    "featureType": "road.highway",
    "elementType": "geometry.stroke",
    "stylers": [
      {
        "color": "#2c1e40"
      }
    ]
  },
  {
    "featureType": "road.highway",
    "elementType": "labels.text.fill",
    "stylers": [
      {
        "color": "#1e142c"
      }
    ]
  },
  {
    "featureType": "road.highway",
    "elementType": "labels.text.stroke",
    "stylers": [
      {
        "color": "#49336a"
      }
    ]
  },
  {
    "featureType": "transit",
    "stylers": [
      {
        "visibility": "off"
      }
    ]
  },
  {
    "featureType": "transit",
    "elementType": "labels.text.fill",
    "stylers": [
      {
        "color": "#e7ffdc"
      }
    ]
  },
  {
    "featureType": "transit",
    "elementType": "labels.text.stroke",
    "stylers": [
      {
        "color": "#1c1328"
      }
    ]
  },
  {
    "featureType": "transit.line",
    "elementType": "geometry.fill",
    "stylers": [
      {
        "color": "#2b1e3e"
      }
    ]
  },
  {
    "featureType": "transit.station",
    "elementType": "geometry",
    "stylers": [
      {
        "color": "#211630"
      }
    ]
  },
  {
    "featureType": "water",
    "elementType": "geometry",
    "stylers": [
      {
        "color": "#030204"
      }
    ]
  },
  {
    "featureType": "water",
    "elementType": "labels.text.fill",
    "stylers": [
      {
        "color": "#3f2c5c"
      }
    ]
  }
]
